{
    "resourceType": "Condition",
    "id": "example",
    "clinicalStatus": {
      "coding": [
        {
          "system": "http://terminology.hl7.org/CodeSystem/condition-clinical",
          "code": "active"
        }
      ]
    },
    "code": {
      "coding": [
        {
          "system": "http://snomed.info/sct",
          "code": "44054006",
          "display": "Diabetes mellitus type 2"
        }
      ],
      "text": "Type 2 Diabetes"
    },
    "subject": {
      "reference": "Patient/example"
    },
    "onsetDateTime": "2015-03-01"
  }
  